[
  {
    "name": "aaaebea",
    "tel": "6565642137"
  },
  {
    "name": "cbecbec",
    "tel": "1275161346"
  },
  {
    "name": "edbbedb",
    "tel": "4454232743"
  },
  {
    "name": "edbeebc",
    "tel": "4416212152"
  },
  {
    "name": "dbcebce",
    "tel": "7374637313"
  },
  {
    "name": "cebebcb",
    "tel": "6154374324"
  },
  {
    "name": "edbbcbb",
    "tel": "1544254414"
  },
  {
    "name": "aebdcbb",
    "tel": "1661646673"
  },
  {
    "name": "ccdedcd",
    "tel": "2356214142"
  },
  {
    "name": "adbedda",
    "tel": "4453616476"
  }
]